MANIFEST.in
README.rst
setup.cfg
setup.py
docs/docs_requirements.txt
word_ladder/__init__.py
word_ladder/cli.py
word_ladder/errors.py
word_ladder/word_ladder.py
word_ladder.egg-info/PKG-INFO
word_ladder.egg-info/SOURCES.txt
word_ladder.egg-info/dependency_links.txt
word_ladder.egg-info/entry_points.txt
word_ladder.egg-info/not-zip-safe
word_ladder.egg-info/requires.txt
word_ladder.egg-info/top_level.txt