Metadata-Version: 1.1
Name: word-ladder
Version: 1.0.1
Summary: Word ladder find path between two words, changing one letter each step
Home-page: https://github.com/snebel29/word_ladder
Author: Sven Nebel
Author-email: nebel.sven@gmail.com
License: GPL
Download-URL: https://github.com/snebel29/word_ladder/archive/1.0.1.tar.gz
Keywords: word,ladder
Platform: UNKNOWN
Classifier: License :: OSI Approved :: GNU General Public License (GPL)
Classifier: Natural Language :: English
Classifier: Intended Audience :: Developers
Classifier: Programming Language :: Python
Classifier: Programming Language :: Python :: 3.4
Classifier: Programming Language :: Python :: Implementation :: CPython
Classifier: Operating System :: POSIX
